spotify_playlist/__init__.py
spotify_playlist/__main__.py
spotify_playlist/__version__.py
spotify_playlist/cli.py
spotify_playlist/util.py
spotify_playlist-0.3.6.dist-info/LICENSE
spotify_playlist-0.3.6.dist-info/METADATA
spotify_playlist-0.3.6.dist-info/WHEEL
spotify_playlist-0.3.6.dist-info/entry_points.txt
spotify_playlist-0.3.6.dist-info/top_level.txt
spotify_playlist-0.3.6.dist-info/RECORD
