Metadata-Version: 2.1
Name: spotify-playlist
Version: 0.3.6
Summary: spotify-playlist
Author-email: T Lan <t.lan@uq.edu.au>
License: MIT
Project-URL: homepage, https://github.com/387809109/spotify-playlist
Classifier: License :: OSI Approved :: MIT License
Classifier: Programming Language :: Python
Classifier: Programming Language :: Python :: 3
Requires-Python: >=3.8.0
License-File: LICENSE
Requires-Dist: click
Requires-Dist: spotipy
Requires-Dist: unidecode
